colorclade/__init__.py
colorclade/_biopython_color_tree.py
colorclade/_biopython_draw_colorclade_tree.py
colorclade/_biopython_pare_tree.py
colorclade/_biopython_sort_tree.py
colorclade/_draw_colorclade_tree.py
colorclade/_hash_name.py
colorclade/_matplotlib_drop_overlapping_labels.py
colorclade/_val_to_color_hls.py
colorclade/_val_to_color_muted.py
colorclade-0.2.0.dist-info/LICENSE
colorclade-0.2.0.dist-info/METADATA
colorclade-0.2.0.dist-info/WHEEL
colorclade-0.2.0.dist-info/top_level.txt
colorclade-0.2.0.dist-info/RECORD
