Metadata-Version: 2.1
Name: colorclade
Version: 0.2.0
Summary: colorclade draws phylogenies with hierarchical coloring for easier visual comparison.
Author-email: Matthew Andres Moreno <m.more500@gmail.com>
License: MIT license
Project-URL: homepage, https://github.com/mmore500/colorclade
Project-URL: documentation, https://github.com/mmore500/colorclade
Project-URL: repository, https://github.com/mmore500/colorclade
Project-URL: tracker, https://github.com/mmore500/colorclade/issues
Classifier: Development Status :: 3 - Alpha
Classifier: Intended Audience :: Developers
Classifier: Topic :: Software Development :: Libraries :: Python Modules
Classifier: License :: OSI Approved :: MIT License
Classifier: Programming Language :: Python :: 3
Classifier: Programming Language :: Python :: 3.8
Classifier: Programming Language :: Python :: 3.9
Classifier: Programming Language :: Python :: 3.10
Classifier: Programming Language :: Python :: 3.11
Classifier: Programming Language :: Python :: 3.12
Requires-Python: >=3.8
License-File: LICENSE
Requires-Dist: alifedata-phyloinformatics-convert
Requires-Dist: Biopython
Requires-Dist: matplotlib
Requires-Dist: numpy
Requires-Dist: opytional
Requires-Dist: seaborn
Provides-Extra: dev
Requires-Dist: black ==22.10.0 ; extra == 'dev'
Requires-Dist: bump2version ==1.0.1 ; extra == 'dev'
Requires-Dist: isort ==5.12.0 ; extra == 'dev'
Requires-Dist: pip-tools ==7.3.0 ; extra == 'dev'
Requires-Dist: pytest ==6.2.5 ; extra == 'dev'
Requires-Dist: ruff ==0.1.11 ; extra == 'dev'
